google_maps_sdk-1.0.0.dist-info/licenses/LICENSE
googlemapsplatformcoreapis/__init__.py
googlemapsplatformcoreapis/api_helper.py
googlemapsplatformcoreapis/configuration.py
googlemapsplatformcoreapis/googlemapsplatformcoreapis_client.py
googlemapsplatformcoreapis/controllers/__init__.py
googlemapsplatformcoreapis/controllers/address_validation_api_controller.py
googlemapsplatformcoreapis/controllers/aerial_view_api_controller.py
googlemapsplatformcoreapis/controllers/air_quality_api_controller.py
googlemapsplatformcoreapis/controllers/autocomplete_controller.py
googlemapsplatformcoreapis/controllers/base_controller.py
googlemapsplatformcoreapis/controllers/directions_api_legacy_controller.py
googlemapsplatformcoreapis/controllers/distance_matrix_api_legacy_controller.py
googlemapsplatformcoreapis/controllers/elevation_api_controller.py
googlemapsplatformcoreapis/controllers/geocoding_api_controller.py
googlemapsplatformcoreapis/controllers/geolocation_api_controller.py
googlemapsplatformcoreapis/controllers/places_api_controller.py
googlemapsplatformcoreapis/controllers/places_api_legacy_controller.py
googlemapsplatformcoreapis/controllers/pollen_api_controller.py
googlemapsplatformcoreapis/controllers/roads_api_controller.py
googlemapsplatformcoreapis/controllers/routes_api_controller.py
googlemapsplatformcoreapis/controllers/solar_api_controller.py
googlemapsplatformcoreapis/controllers/street_view_api_controller.py
googlemapsplatformcoreapis/controllers/time_zone_api_controller.py
googlemapsplatformcoreapis/controllers/weather_api_controller.py
googlemapsplatformcoreapis/exceptions/__init__.py
googlemapsplatformcoreapis/exceptions/api_exception.py
googlemapsplatformcoreapis/exceptions/m_400_badrequest_4_exception.py
googlemapsplatformcoreapis/exceptions/m_400_badrequest_exception.py
googlemapsplatformcoreapis/exceptions/m_404_notfound_exception.py
googlemapsplatformcoreapis/http/__init__.py
googlemapsplatformcoreapis/http/http_call_back.py
googlemapsplatformcoreapis/http/http_method_enum.py
google_maps_sdk-1.0.0.dist-info/METADATA
google_maps_sdk-1.0.0.dist-info/WHEEL
google_maps_sdk-1.0.0.dist-info/top_level.txt
google_maps_sdk-1.0.0.dist-info/RECORD
